tinycircuits_bma250/__init__.py
tinycircuits_bma250/tinycircuits_bma250.py
tinycircuits_bma250-0.0.2.dist-info/LICENSE
tinycircuits_bma250-0.0.2.dist-info/METADATA
tinycircuits_bma250-0.0.2.dist-info/WHEEL
tinycircuits_bma250-0.0.2.dist-info/top_level.txt
tinycircuits_bma250-0.0.2.dist-info/RECORD
