Metadata-Version: 2.1
Name: tinycircuits-bma250
Version: 0.0.2
Summary: Wireling Accelerometer Sensor Python library
Home-page: https://github.com/TinyCircuits/TinyCircuits-Wireling-Accelerometer-Python-AST1001
Author: TinyCircuits
Author-email: info@tinycircuits.com
License: UNKNOWN
Platform: UNKNOWN
Classifier: Programming Language :: Python :: 3
Classifier: License :: OSI Approved :: GNU General Public License v3 (GPLv3)
Classifier: Operating System :: OS Independent
Requires-Python: >=3.6
